my_bencoding/__init__.py
my_bencoding/bencoding_decode.py
my_bencoding/bencoding_encode.py
my_bencoding-0.1.1.dist-info/DESCRIPTION.rst
my_bencoding-0.1.1.dist-info/METADATA
my_bencoding-0.1.1.dist-info/RECORD
my_bencoding-0.1.1.dist-info/WHEEL
my_bencoding-0.1.1.dist-info/metadata.json
my_bencoding-0.1.1.dist-info/top_level.txt
