Metadata-Version: 2.0
Name: my-bencoding
Version: 0.1.1
Summary: bencoding in python2 and python3, for code and study
Home-page: https://windard.com
Author: Windard Yang
Author-email: windard@qq.com
License: MIT
Keywords: Bencoding In Python2 And Python3
Platform: UNKNOWN
Requires-Python: >=2.6
